jupyterlab_markup_expr/__init__.py
jupyterlab_markup_expr/_version.py
jupyterlab_markup_expr/labextension/build_log.json
jupyterlab_markup_expr/labextension/package.json
jupyterlab_markup_expr/labextension/static/37.f2dcf6b5e4b271dd1c5a.js
jupyterlab_markup_expr/labextension/static/747.1453c9765da5af76349b.js
jupyterlab_markup_expr/labextension/static/lib_index_js.a16815202d7374266f9c.js
jupyterlab_markup_expr/labextension/static/lib_index_js.a16815202d7374266f9c.js.map
jupyterlab_markup_expr/labextension/static/remoteEntry.a52c219562a95d8c2ce8.js
jupyterlab_markup_expr/labextension/static/remoteEntry.f9148192ae4752ebfca6.js
jupyterlab_markup_expr/labextension/static/remoteEntry.f9148192ae4752ebfca6.js.map
jupyterlab_markup_expr/labextension/static/style.js
jupyterlab_markup_expr/labextension/static/style_index_js.0a728767879e3de2512c.js
jupyterlab_markup_expr/labextension/static/style_index_js.0a728767879e3de2512c.js.map
jupyterlab_markup_expr/labextension/static/third-party-licenses.json
jupyterlab_markup_expr/labextension/static/vendors-node_modules_css-loader_dist_runtime_api_js-node_modules_css-loader_dist_runtime_cssW-72eba1.5eca5885a0f7cbe32411.js
jupyterlab_markup_expr/labextension/static/vendors-node_modules_css-loader_dist_runtime_api_js-node_modules_css-loader_dist_runtime_cssW-72eba1.5eca5885a0f7cbe32411.js.map
jupyterlab_markup_expr-0.1.1.data/data/share/jupyter/labextensions/@agoose77/jupyterlab-markup-expr/install.json
jupyterlab_markup_expr-0.1.1.data/data/share/jupyter/labextensions/@agoose77/jupyterlab-markup-expr/package.json
jupyterlab_markup_expr-0.1.1.data/data/share/jupyter/labextensions/@agoose77/jupyterlab-markup-expr/static/37.f2dcf6b5e4b271dd1c5a.js
jupyterlab_markup_expr-0.1.1.data/data/share/jupyter/labextensions/@agoose77/jupyterlab-markup-expr/static/747.1453c9765da5af76349b.js
jupyterlab_markup_expr-0.1.1.data/data/share/jupyter/labextensions/@agoose77/jupyterlab-markup-expr/static/remoteEntry.a52c219562a95d8c2ce8.js
jupyterlab_markup_expr-0.1.1.dist-info/LICENSE
jupyterlab_markup_expr-0.1.1.dist-info/METADATA
jupyterlab_markup_expr-0.1.1.dist-info/WHEEL
jupyterlab_markup_expr-0.1.1.dist-info/top_level.txt
jupyterlab_markup_expr-0.1.1.dist-info/RECORD
